setup.py
rw/__init__.py
rw.egg-info/PKG-INFO
rw.egg-info/SOURCES.txt
rw.egg-info/dependency_links.txt
rw.egg-info/requires.txt
rw.egg-info/top_level.txt
scripts/rw