Metadata-Version: 1.0
Name: rw
Version: 0.0.2
Summary: Generate random words (e.g. for passwords)
Home-page: http://github.com/Pringley/rw
Author: Ben Pringle
Author-email: ben.pringle@gmail.com
License: MIT
Platform: UNKNOWN
